{
   "sample_number": 29,
   "defaults": {
      "pre_anneal_delay_time": 0.0,
      "anneal_start_temperature": 40.0,
      "anneal_cool_temperature": 60,
      "anneal_temperature": 200.0,
      "anneal_ramp_rate": 0.75,
      "anneal_hold_time": 450,
      "dispense_volume": 0.1,
      "spin_speed": 1000,
      "spin_time": 60,
      "drop_volume": 0.098,
      "drop_height": 1.5,
      "drop_dispense_velocity": 0.3,
      "post_drop_delay": 0
   },
   "robot_parameters": {
      "Pd_ACN": {
         "stock_tray_name": "stock_tray",
         "index": [
            5,
            6,
            7,
            13,
            14,
            15
         ],
         "chemical_name": "Pd(NO3)2_ACN",
         "concentration": {
            "value": 12.0,
            "units": "mg/ml"
         },
         "molar_weight": {
            "value": 1.0,
            "units": "mg"
         },
         "solvent": "ACN",
         "density": {
            "value": 0.798,
            "units": "g/cm^3"
         }
      },
      "gly_H2O": {
         "stock_tray_name": "stock_tray",
         "index": [
            0,
            1,
            2
         ],
         "chemical_name": "glycine_H2O",
         "concentration": {
            "value": 12,
            "units": "mg/ml"
         },
         "molar_weight": {
            "value": 1.0,
            "units": "mg"
         },
         "solvent": "H2O",
         "density": {
            "value": 1.012,
            "units": "g/cm^3"
         }
      },
      "acac_H2O": {
         "stock_tray_name": "stock_tray",
         "index": [
            8,
            9,
            10
         ],
         "chemical_name": "acetylacetone_H2O",
         "concentration": {
            "value": 12,
            "units": "mg/ml"
         },
         "molar_weight": {
            "value": 1.0,
            "units": "mg"
         },
         "solvent": "H2O",
         "density": {
            "value": 1.012,
            "units": "g/cm^3"
         }
      },
      "dilutant": {
         "stock_tray_name": "stock_tray",
         "index": [
            3,
            4,
            11,
            12
         ],
         "chemical_name": "H2O",
         "concentration": {
            "value": 1,
            "units": "mg/ml"
         },
         "molar_weight": {
            "value": 1.0,
            "units": "mg"
         },
         "solvent": "H2O",
         "density": {
            "value": 1.0,
            "units": "g/cm^3"
         }
      }
   },
   "layers": [
      {
         "pre_anneal_delay_time": 0.0,
         "anneal_start_temperature": 40.0,
         "anneal_cool_temperature": 60,
         "anneal_temperature": 253.3841552734375,
         "anneal_ramp_rate": 0.75,
         "anneal_hold_time": 450,
         "dispense_volume": 0.1,
         "spin_speed": 1000,
         "spin_time": 60,
         "drop_volume": 0.098,
         "drop_height": 1.5,
         "drop_dispense_velocity": 0.3,
         "post_drop_delay": 0,
         "chemicals": [
            {
               "name": "Pd_ACN",
               "volume": 0.15048518026695545,
               "density": 0.798,
               "index": [
                  5,
                  6,
                  7,
                  13,
                  14,
                  15
               ]
            },
            {
               "name": "gly_H2O",
               "volume": 0.02159648179190458,
               "density": 1.012,
               "index": [
                  0,
                  1,
                  2
               ]
            },
            {
               "name": "acac_H2O",
               "volume": 0.017553091953168315,
               "density": 1.012,
               "index": [
                  8,
                  9,
                  10
               ]
            },
            {
               "name": "dilutant",
               "volume": 0.010365245987971656,
               "density": 1.0,
               "index": [
                  3,
                  4,
                  11,
                  12
               ]
            }
         ]
      }
   ],
   "dispense": [
      {
         "Pd_ACN": {
            "status": true,
            "total_mass": 0.12159999999999993,
            "total_volume": 0.15238095238095228,
            "target_volume": 0.15048518026695545,
            "volumes": {
               "target": [
                  0.15048518026695545,
                  0.06226462888850905
               ],
               "calibrated": [
                  0.1,
                  0.07127801975987091
               ],
               "dispensed": [
                  0.08822055137844641,
                  0.06416040100250588
               ],
               "error": [
                  0.011779448621553598,
                  0.007117618757365038
               ],
               "pump_draws": [
                  0.1,
                  0.07127801975987091
               ]
            },
            "stock_trips": [
               0,
               1
            ]
         },
         "gly_H2O": {
            "status": true,
            "total_mass": 0.021400000000000308,
            "total_volume": 0.021146245059288842,
            "target_volume": 0.02159648179190458,
            "volumes": {
               "target": [
                  0.02159648179190458
               ],
               "calibrated": [
                  0.029035759978395085
               ],
               "dispensed": [
                  0.021146245059288842
               ],
               "error": [
                  0.007889514919106243
               ],
               "pump_draws": [
                  0.029035759978395085
               ]
            },
            "stock_trips": [
               0
            ]
         },
         "acac_H2O": {
            "status": true,
            "total_mass": 0.019099999999999895,
            "total_volume": 0.01887351778656116,
            "target_volume": 0.017553091953168315,
            "volumes": {
               "target": [
                  0.017553091953168315
               ],
               "calibrated": [
                  0.023467124844275468
               ],
               "dispensed": [
                  0.01887351778656116
               ],
               "error": [
                  0.004593607057714309
               ],
               "pump_draws": [
                  0.023467124844275468
               ]
            },
            "stock_trips": [
               0
            ]
         },
         "dilutant": {
            "status": true,
            "total_mass": 0.01100000000000012,
            "total_volume": 0.01100000000000012,
            "target_volume": 0.010365245987971656,
            "volumes": {
               "target": [
                  0.010365245987971656
               ],
               "calibrated": [
                  0.016882941268430807
               ],
               "dispensed": [
                  0.01100000000000012
               ],
               "error": [
                  0.005882941268430687
               ],
               "pump_draws": [
                  0.016882941268430807
               ]
            },
            "stock_trips": [
               0
            ]
         }
      }
   ],
   "requested": {
      "fuel_oxidizer_ratio": 1.040701985359192,
      "acac_amount": 0.6190412044525146,
      "concentration": 0.011378085240721703,
      "anneal_temperature": 253.3841552734375
   },
   "realized": {
      "fuel_oxidizer_ratio": 1.0674517008183622,
      "acac_amount": 0.6408553038760352,
      "concentration": 0.011161253506619652,
      "anneal_temperature": 253.3841552734375
   },
   "robot_requested": {
      "Pd_ACN": 0.15048518026695545,
      "gly_H2O": 0.02159648179190458,
      "acac_H2O": 0.017553091953168315,
      "dilutant": 0.010365245987971656,
      "anneal_temperature": 253.3841552734375
   },
   "robot_realized": {
      "Pd_ACN": 0.15238095238095228,
      "gly_H2O": 0.021146245059288842,
      "acac_H2O": 0.01887351778656116,
      "dilutant": 0.01100000000000012,
      "anneal_temperature": 253.3841552734375
   },
   "cost": [
      {
         "objective": "condxrfman_avg",
         "value": 1.2603137200112314e-07
      },
      {
         "objective": "anneal_temperature",
         "value": 253.3841552734375
      }
   ]
}