{
   "sample_number": 66,
   "defaults": {
      "pre_anneal_delay_time": 0.0,
      "anneal_start_temperature": 40.0,
      "anneal_cool_temperature": 60,
      "anneal_temperature": 200.0,
      "anneal_ramp_rate": 0.75,
      "anneal_hold_time": 450,
      "dispense_volume": 0.1,
      "spin_speed": 1000,
      "spin_time": 60,
      "drop_volume": 0.098,
      "drop_height": 1.5,
      "drop_dispense_velocity": 0.3,
      "post_drop_delay": 0
   },
   "robot_parameters": {
      "Pd_ACN": {
         "stock_tray_name": "stock_tray",
         "index": [
            5,
            6,
            7,
            13
         ],
         "chemical_name": "Pd(NO3)2_ACN",
         "concentration": {
            "value": 12.0,
            "units": "mg/ml"
         },
         "molar_weight": {
            "value": 1.0,
            "units": "mg"
         },
         "solvent": "ACN",
         "density": {
            "value": 0.798,
            "units": "g/cm^3"
         }
      },
      "gly_H2O": {
         "stock_tray_name": "stock_tray",
         "index": [
            0,
            1,
            2
         ],
         "chemical_name": "glycine_H2O",
         "concentration": {
            "value": 12,
            "units": "mg/ml"
         },
         "molar_weight": {
            "value": 1.0,
            "units": "mg"
         },
         "solvent": "H2O",
         "density": {
            "value": 1.012,
            "units": "g/cm^3"
         }
      },
      "acac_H2O": {
         "stock_tray_name": "stock_tray",
         "index": [
            8,
            9,
            10
         ],
         "chemical_name": "acetylacetone_H2O",
         "concentration": {
            "value": 12,
            "units": "mg/ml"
         },
         "molar_weight": {
            "value": 1.0,
            "units": "mg"
         },
         "solvent": "H2O",
         "density": {
            "value": 1.012,
            "units": "g/cm^3"
         }
      },
      "dilutant": {
         "stock_tray_name": "stock_tray",
         "index": [
            3,
            4,
            11,
            12
         ],
         "chemical_name": "H2O",
         "concentration": {
            "value": 1,
            "units": "mg/ml"
         },
         "molar_weight": {
            "value": 1.0,
            "units": "mg"
         },
         "solvent": "H2O",
         "density": {
            "value": 1.0,
            "units": "g/cm^3"
         }
      }
   },
   "layers": [
      {
         "pre_anneal_delay_time": 0.0,
         "anneal_start_temperature": 40.0,
         "anneal_cool_temperature": 60,
         "anneal_temperature": 275.42364501953125,
         "anneal_ramp_rate": 0.75,
         "anneal_hold_time": 450,
         "dispense_volume": 0.1,
         "spin_speed": 1000,
         "spin_time": 60,
         "drop_volume": 0.098,
         "drop_height": 1.5,
         "drop_dispense_velocity": 0.3,
         "post_drop_delay": 0,
         "chemicals": [
            {
               "name": "Pd_ACN",
               "volume": 0.10884326332376788,
               "density": 0.798,
               "index": [
                  5,
                  6,
                  7,
                  13
               ]
            },
            {
               "name": "gly_H2O",
               "volume": 0.038447851457909826,
               "density": 1.012,
               "index": [
                  0,
                  1,
                  2
               ]
            },
            {
               "name": "acac_H2O",
               "volume": 0.006709809497614708,
               "density": 1.012,
               "index": [
                  8,
                  9,
                  10
               ]
            },
            {
               "name": "dilutant",
               "volume": 0.04599907572070758,
               "density": 1.0,
               "index": [
                  3,
                  4,
                  11,
                  12
               ]
            }
         ]
      }
   ],
   "dispense": [
      {
         "Pd_ACN": {
            "status": true,
            "total_mass": 0.0889000000000002,
            "total_volume": 0.11140350877193007,
            "target_volume": 0.10884326332376788,
            "volumes": {
               "target": [
                  0.10884326332376788,
                  0.02287835104306614
               ],
               "calibrated": [
                  0.1,
                  0.027660246408145055
               ],
               "dispensed": [
                  0.08596491228070174,
                  0.025438596491228326
               ],
               "error": [
                  0.014035087719298261,
                  0.002221649916916729
               ],
               "pump_draws": [
                  0.1,
                  0.027660246408145055
               ]
            },
            "stock_trips": [
               0,
               1
            ]
         },
         "gly_H2O": {
            "status": true,
            "total_mass": 0.040600000000000414,
            "total_volume": 0.04011857707509922,
            "target_volume": 0.038447851457909826,
            "volumes": {
               "target": [
                  0.038447851457909826,
                  0.008309511536961238,
                  0.004258128137751539
               ],
               "calibrated": [
                  0.047091769137818935,
                  0.015024526811818893,
                  0.009683940951526693
               ],
               "dispensed": [
                  0.03013833992094859,
                  0.004051383399209698,
                  0.005928853754940936
               ],
               "error": [
                  0.016953429216870347,
                  0.010973143412609195,
                  0.003755087196585757
               ],
               "pump_draws": [
                  0.047091769137818935,
                  0.015024526811818893,
                  0.009683940951526693
               ]
            },
            "stock_trips": [
               0,
               1,
               2
            ]
         },
         "acac_H2O": {
            "status": true,
            "total_mass": 0.007700000000000262,
            "total_volume": 0.007608695652174172,
            "target_volume": 0.006709809497614708,
            "volumes": {
               "target": [
                  0.006709809497614708
               ],
               "calibrated": [
                  0.011866815095957864
               ],
               "dispensed": [
                  0.007608695652174172
               ],
               "error": [
                  0.004258119443783692
               ],
               "pump_draws": [
                  0.011866815095957864
               ]
            },
            "stock_trips": [
               0
            ]
         },
         "dilutant": {
            "status": true,
            "total_mass": 0.04830000000000023,
            "total_volume": 0.04830000000000023,
            "target_volume": 0.04599907572070758,
            "volumes": {
               "target": [
                  0.04599907572070758
               ],
               "calibrated": [
                  0.05506671220823532
               ],
               "dispensed": [
                  0.04830000000000023
               ],
               "error": [
                  0.00676671220823509
               ],
               "pump_draws": [
                  0.05506671220823532
               ]
            },
            "stock_trips": [
               0
            ]
         }
      }
   ],
   "requested": {
      "fuel_oxidizer_ratio": 1.3163381814956665,
      "acac_amount": 0.258658766746521,
      "concentration": 0.009240055456757545,
      "anneal_temperature": 275.42364501953125
   },
   "realized": {
      "fuel_oxidizer_ratio": 1.3720818565914643,
      "acac_amount": 0.27492698339242,
      "concentration": 0.00887603549327243,
      "anneal_temperature": 275.42364501953125
   },
   "robot_requested": {
      "Pd_ACN": 0.10884326332376788,
      "gly_H2O": 0.038447851457909826,
      "acac_H2O": 0.006709809497614708,
      "dilutant": 0.04599907572070758,
      "anneal_temperature": 275.42364501953125
   },
   "robot_realized": {
      "Pd_ACN": 0.11140350877193007,
      "gly_H2O": 0.04011857707509922,
      "acac_H2O": 0.007608695652174172,
      "dilutant": 0.04830000000000023,
      "anneal_temperature": 275.42364501953125
   },
   "cost": [
      {
         "objective": "condxrfman_avg",
         "value": 6.821400995677268e-07
      },
      {
         "objective": "anneal_temperature",
         "value": 275.42364501953125
      }
   ]
}